piuma/__init__.py
piuma/__version__.py
piuma/piuma.py
piuma/storage/__init__.py
piuma/storage/storage.py
piuma-1.1.2.dist-info/LICENSE
piuma-1.1.2.dist-info/METADATA
piuma-1.1.2.dist-info/WHEEL
piuma-1.1.2.dist-info/top_level.txt
piuma-1.1.2.dist-info/RECORD
