Metadata-Version: 2.1
Name: piuma
Version: 1.1.2
Summary: An ultra-lighweight document oriented database
Home-page: https://github.com/emit07/piuma
Author: Alessandro De Leo
Author-email: emit07@protonmail.com
License: gpl-3.0
Keywords: python,database,document oriented
Platform: UNKNOWN
